{
  "version": "5",
  "dialect": "mysql",
  "id": "c25bbd28-1778-40ce-aa28-26265b8f086f",
  "prevId": "1003127f-3231-4923-8ac2-7ed1c35655cf",
  "tables": {
    "orcamento": {
      "name": "orcamento",
      "columns": {
        "id": {
          "name": "id",
          "type": "int",
          "primaryKey": false,
          "notNull": true,
          "autoincrement": true
        },
        "nome": {
          "name": "nome",
          "type": "varchar(50)",
          "primaryKey": false,
          "notNull": false,
          "autoincrement": false
        },
        "data": {
          "name": "data",
          "type": "date",
          "primaryKey": false,
          "notNull": false,
          "autoincrement": false
        }
      },
      "indexes": {},
      "foreignKeys": {},
      "compositePrimaryKeys": {
        "orcamento_id": {
          "name": "orcamento_id",
          "columns": [
            "id"
          ]
        }
      },
      "uniqueConstraints": {}
    },
    "produtoOrcamento": {
      "name": "produtoOrcamento",
      "columns": {
        "id": {
          "name": "id",
          "type": "int",
          "primaryKey": false,
          "notNull": true,
          "autoincrement": true
        },
        "nome": {
          "name": "nome",
          "type": "varchar(50)",
          "primaryKey": false,
          "notNull": false,
          "autoincrement": false
        },
        "data": {
          "name": "data",
          "type": "float",
          "primaryKey": false,
          "notNull": false,
          "autoincrement": false
        },
        "orcamentoId": {
          "name": "orcamentoId",
          "type": "int",
          "primaryKey": false,
          "notNull": false,
          "autoincrement": false
        }
      },
      "indexes": {},
      "foreignKeys": {},
      "compositePrimaryKeys": {
        "produtoOrcamento_id": {
          "name": "produtoOrcamento_id",
          "columns": [
            "id"
          ]
        }
      },
      "uniqueConstraints": {}
    }
  },
  "schemas": {},
  "_meta": {
    "schemas": {},
    "tables": {},
    "columns": {}
  }
}